{
  "title": "Daßperre",
  "compat": "7.0-12.1.2",
  "desc": "<p>A LockHTML remake for one of my favorite GroovyLock themes. The original theme is TheStudent's GRAND LS, this is optimised for LockHTML with various settings.</p>",
  "screenshots": [
    "com.evaneliasyoung.dassperre/screen1.png",
    "com.evaneliasyoung.dassperre/screen2.png",
    "com.evaneliasyoung.dassperre/screen3.png"
  ],
  "changelog": [
    {
      "version": "1.0.4",
      "changes": [
        "Format updates"
      ],
      "date": "2019-03-16"
    },
    {
      "version": "1.0.3",
      "changes": [
        "Format updates"
      ],
      "date": "2019-03-16"
    },
    {
      "version": "1.0.2",
      "changes": [
        "Actually fixed the 24 Hour switch"
      ],
      "date": "2017-03-29"
    },
    {
      "version": "1.0.1",
      "changes": [
        "Fixed the 24 Hour switch"
      ],
      "date": "2017-03-29"
    },
    {
      "version": "1.0",
      "changes": [
        "Initial Release"
      ],
      "date": "2017-03-29"
    }
  ]
}
